tests/__init__.py
tests/base.py
tests/test_biffh.py
tests/test_cell.py
tests/test_formats.py
tests/test_formulas.py
tests/test_missing_records.py
tests/test_open_workbook.py
tests/test_sheet.py
tests/test_workbook.py
tests/test_xldate.py
tests/test_xldate_to_datetime.py
tests/test_xlsx_comments.py
tests/test_xlsx_parse.py
xlrdinc/__init__.py
xlrdinc/biffh.py
xlrdinc/book.py
xlrdinc/compdoc.py
xlrdinc/formatting.py
xlrdinc/formula.py
xlrdinc/info.py
xlrdinc/sheet.py
xlrdinc/timemachine.py
xlrdinc/xldate.py
xlrdinc/xlsx.py
xlrdinc-1.2.0.4.data/scripts/runxlrd.py
xlrdinc-1.2.0.4.dist-info/LICENSE
xlrdinc-1.2.0.4.dist-info/METADATA
xlrdinc-1.2.0.4.dist-info/WHEEL
xlrdinc-1.2.0.4.dist-info/top_level.txt
xlrdinc-1.2.0.4.dist-info/RECORD
